MANIFEST.in
setup.py
esyimg/__init__.py
esyimg/__main__.py
esyimg/graph_objects.py
esyimg/multi_gaussian.py
esyimg/process_bar.py
esyimg/server.py
esyimg/visdom_util.py
esyimg.egg-info/PKG-INFO
esyimg.egg-info/SOURCES.txt
esyimg.egg-info/dependency_links.txt
esyimg.egg-info/top_level.txt