Metadata-Version: 2.1
Name: esyimg
Version: 39.2025.8.22.15.53
Summary: a python lib for project files
Home-page: http://www.xxxxx.com/
Author: Quanfa
Author-email: quanfa@tju.edu.cn
License: MIT
